credzer/credzer.py
credzer/lib/args.py
credzer/lib/conf.py
credzer/lib/display.py
credzer/lib/model.py
credzer/lib/parser.py
credzer/lib/router.py
credzer/lib/static.py
credzer-0.1.1.dist-info/METADATA
credzer-0.1.1.dist-info/WHEEL
credzer-0.1.1.dist-info/entry_points.txt
credzer-0.1.1.dist-info/RECORD
