Metadata-Version: 2.1
Name: credzer
Version: 0.1.1
Summary: One to rule them all
Author: shoxxdj
Author-email: shoxx@shoxxdj.fr
Requires-Python: >=3.10,<4.0
Classifier: Programming Language :: Python :: 3
Classifier: Programming Language :: Python :: 3.10
Classifier: Programming Language :: Python :: 3.11
Requires-Dist: tinydb (>=4.7.0,<5.0.0)
